# 字节码练习题01总结

## 原始java代码

```java
public class Hello {

    public void hello() {
        int age = 10;
        if (age <= 20) {
            System.out.println("you are a boy!");
        }
        age = age + 20;
        if (age > 20) {
            System.out.println("After 20 years, you are a man");
        }

        for(int i = 0; i < 5; i++) {
            System.out.println("current index is: " + i);
        }
    }

    public static void main(String[] args) {
        new Hello().hello();
    }

}
```

## javap -c -verbose后

```java
Classfile /E:/local-code/java/����ʱ��/java����ѵ��Ӫ/JAVA-000/Week_01/Hello.class
  Last modified 2020-10-18; size 873 bytes
  MD5 checksum 1470cde921d2963d4d55862866d3059f
  Compiled from "Hello.java"
public class Hello
  minor version: 0
  major version: 52
  flags: ACC_PUBLIC, ACC_SUPER
Constant pool:
   #1 = Methodref          #15.#26        // java/lang/Object."<init>":()V
   #2 = Fieldref           #27.#28        // java/lang/System.out:Ljava/io/PrintStream;
   #3 = String             #29            // you are a boy!
   #4 = Methodref          #30.#31        // java/io/PrintStream.println:(Ljava/lang/String;)V
   #5 = String             #32            // After 20 years, you are a man
   #6 = Class              #33            // java/lang/StringBuilder
   #7 = Methodref          #6.#26         // java/lang/StringBuilder."<init>":()V
   #8 = String             #34            // current index is:
   #9 = Methodref          #6.#35         // java/lang/StringBuilder.append:(Ljava/lang/String;)Ljava/lang/StringBuilder;
  #10 = Methodref          #6.#36         // java/lang/StringBuilder.append:(I)Ljava/lang/StringBuilder;
  #11 = Methodref          #6.#37         // java/lang/StringBuilder.toString:()Ljava/lang/String;
  #12 = Class              #38            // Hello
  #13 = Methodref          #12.#26        // Hello."<init>":()V
  #14 = Methodref          #12.#39        // Hello.hello:()V
  #15 = Class              #40            // java/lang/Object
  #16 = Utf8               <init>
  #17 = Utf8               ()V
  #18 = Utf8               Code
  #19 = Utf8               LineNumberTable
  #20 = Utf8               hello
  #21 = Utf8               StackMapTable
  #22 = Utf8               main
  #23 = Utf8               ([Ljava/lang/String;)V
  #24 = Utf8               SourceFile
  #25 = Utf8               Hello.java
  #26 = NameAndType        #16:#17        // "<init>":()V
  #27 = Class              #41            // java/lang/System
  #28 = NameAndType        #42:#43        // out:Ljava/io/PrintStream;
  #29 = Utf8               you are a boy!
  #30 = Class              #44            // java/io/PrintStream
  #31 = NameAndType        #45:#46        // println:(Ljava/lang/String;)V
  #32 = Utf8               After 20 years, you are a man
  #33 = Utf8               java/lang/StringBuilder
  #34 = Utf8               current index is:
  #35 = NameAndType        #47:#48        // append:(Ljava/lang/String;)Ljava/lang/StringBuilder;
  #36 = NameAndType        #47:#49        // append:(I)Ljava/lang/StringBuilder;
  #37 = NameAndType        #50:#51        // toString:()Ljava/lang/String;
  #38 = Utf8               Hello
  #39 = NameAndType        #20:#17        // hello:()V
  #40 = Utf8               java/lang/Object
  #41 = Utf8               java/lang/System
  #42 = Utf8               out
  #43 = Utf8               Ljava/io/PrintStream;
  #44 = Utf8               java/io/PrintStream
  #45 = Utf8               println
  #46 = Utf8               (Ljava/lang/String;)V
  #47 = Utf8               append
  #48 = Utf8               (Ljava/lang/String;)Ljava/lang/StringBuilder;
  #49 = Utf8               (I)Ljava/lang/StringBuilder;
  #50 = Utf8               toString
  #51 = Utf8               ()Ljava/lang/String;
{
  public Hello();
    descriptor: ()V
    flags: ACC_PUBLIC
    Code:
      stack=1, locals=1, args_size=1
         0: aload_0
         1: invokespecial #1                  // Method java/lang/Object."<init>":()V
         4: return
      LineNumberTable:
        line 1: 0

  public void hello();
    descriptor: ()V
    flags: ACC_PUBLIC
    Code:
      stack=3, locals=3, args_size=1
         0: bipush        10
         2: istore_1
         3: iload_1
         4: bipush        20
         6: if_icmpgt     17
         9: getstatic     #2                  // Field java/lang/System.out:Ljava/io/PrintStream;
        12: ldc           #3                  // String you are a boy!
        14: invokevirtual #4                  // Method java/io/PrintStream.println:(Ljava/lang/String;)V
        17: iload_1
        18: bipush        20
        20: iadd
        21: istore_1
        22: iload_1
        23: bipush        20
        25: if_icmple     36
        28: getstatic     #2                  // Field java/lang/System.out:Ljava/io/PrintStream;
        31: ldc           #5                  // String After 20 years, you are a man
        33: invokevirtual #4                  // Method java/io/PrintStream.println:(Ljava/lang/String;)V
        36: iconst_0
        37: istore_2
        38: iload_2
        39: iconst_5
        40: if_icmpge     74
        43: getstatic     #2                  // Field java/lang/System.out:Ljava/io/PrintStream;
        46: new           #6                  // class java/lang/StringBuilder
        49: dup
        50: invokespecial #7                  // Method java/lang/StringBuilder."<init>":()V
        53: ldc           #8                  // String current index is:
        55: invokevirtual #9                  // Method java/lang/StringBuilder.append:(Ljava/lang/String;)Ljava/lang/StringBuilder;
        58: iload_2
        59: invokevirtual #10                 // Method java/lang/StringBuilder.append:(I)Ljava/lang/StringBuilder;
        62: invokevirtual #11                 // Method java/lang/StringBuilder.toString:()Ljava/lang/String;
        65: invokevirtual #4                  // Method java/io/PrintStream.println:(Ljava/lang/String;)V
        68: iinc          2, 1
        71: goto          38
        74: return
      LineNumberTable:
        line 4: 0
        line 5: 3
        line 6: 9
        line 8: 17
        line 9: 22
        line 10: 28
        line 13: 36
        line 14: 43
        line 13: 68
        line 16: 74
      StackMapTable: number_of_entries = 4
        frame_type = 252 /* append */
          offset_delta = 17
          locals = [ int ]
        frame_type = 18 /* same */
        frame_type = 252 /* append */
          offset_delta = 1
          locals = [ int ]
        frame_type = 250 /* chop */
          offset_delta = 35

  public static void main(java.lang.String[]);
    descriptor: ([Ljava/lang/String;)V
    flags: ACC_PUBLIC, ACC_STATIC
    Code:
      stack=2, locals=1, args_size=1
         0: new           #12                 // class Hello
         3: dup
         4: invokespecial #13                 // Method "<init>":()V
         7: invokevirtual #14                 // Method hello:()V
        10: return
      LineNumberTable:
        line 19: 0
        line 20: 10
}
SourceFile: "Hello.java"

```

## 总结

major version: 52：java8版本

**ACC_PUBLIC**: 共有函数

**ACC_STATIC**：静态函数

stack=1：栈深度

locals=1：本地变量表1个

invokevirtual：调用实例方法

iadd：操作数栈将两个整数相加

ldc：将int, float或String型常量值从常量池中推送至栈顶

iconst_0：将int为0的值推送到栈顶

istore_2：将2放入本地变量列表第3个位置

iinc：将int型的值自增长1

goto：跳转到for循环开始的位置，但是不包含int i = 0;  从读取本地变量表i的值开始，初始化的逻辑不走了



LineNumberTable：记录了源码和字节码位置的对应关系。

